{"type":"Feature","properties":{"hash":"e8605a496593386e","number":"119","street":"NW  41ST ST","unit":"","city":"SEATTLE","district":"KING","region":"","postcode":"98107","id":"324731.0"},"geometry":{"type":"Point","coordinates":[-122.3580529,47.6561133]}}
{"type":"Feature","properties":{"hash":"87d28792bee6b164","number":"115","street":"NW  41ST ST","unit":"","city":"SEATTLE","district":"KING","region":"","postcode":"98107","id":"316864.0"},"geometry":{"type":"Point","coordinates":[-122.3578935,47.6561136]}}
